LICENSE
README.md
setup.py
bfmd/__init__.py
bfmd/blazenet.py
bfmd/inception_v1.py
bfmd/inception_v2.py
bfmd/inception_v3.py
bfmd/mobilenet.py
bfmd/mobilenetv2.py
bfmd/mobilenetv3.py
bfmd/mobilenext.py
bfmd/shufflenet.py
bfmd/shufflenetv2.py
bfmd/xception.py
bfmd.egg-info/PKG-INFO
bfmd.egg-info/SOURCES.txt
bfmd.egg-info/dependency_links.txt
bfmd.egg-info/requires.txt
bfmd.egg-info/top_level.txt
bfmd/efficientnet_pytorch/__init__.py
bfmd/efficientnet_pytorch/model.py
bfmd/efficientnet_pytorch/utils.py